memorylane/__init__.py
memorylane/mem_profile.py
memorylane/memory_readers/__init__.py
memorylane/memory_readers/python.py
memorylane/memory_readers/torch.py
memorylane/py.typed
memorylane-0.1.1.dist-info/WHEEL
memorylane-0.1.1.dist-info/METADATA
memorylane-0.1.1.dist-info/RECORD
