Metadata-Version: 2.3
Name: memorylane
Version: 0.1.1
Summary: Super-lightweight line-by-line memory profiler for numerical Python code. See where those allocations are coming from! Supports NumPy, PyTorch, and more to come.
Author: Peter Sharpe
Author-email: Peter Sharpe <peterdsharpe@gmail.com>
Requires-Dist: rich[jupyter]>=14.1.0
Requires-Dist: torch>=2.0.0 ; extra == 'torch'
Requires-Python: >=3.10
Provides-Extra: torch
